neural/__init__.py
neural/cli.py
neural/example_tensorflow.py
neural/test.py
neural/automatic_hyperparameter_optimization/AHPO.py
neural/automatic_hyperparameter_optimization/__init__.py
neural/automatic_hyperparameter_optimization/hpo.py
neural/code_generation/__init__.py
neural/code_generation/code_generator.py
neural/dashboard/__init__.py
neural/dashboard/dashboard.py
neural/dashboard/tensor_flow.py
neural/execution_optimization/__init__.py
neural/execution_optimization/execution.py
neural/hacky/__init__.py
neural/hacky/hacky.py
neural/hpo/__init__.py
neural/hpo/hpo.py
neural/neural_chat/__init__.py
neural/neural_chat/neural_chat.py
neural/no_code/__init__.py
neural/no_code/no_code.py
neural/parser/__init__.py
neural/parser/parser.py
neural/pretrained_models/__init__.py
neural/pretrained_models/pretrained.py
neural/research_generation/__init__.py
neural/research_generation/research_paper.py
neural/shape_propagation/__init__.py
neural/shape_propagation/data_to_dashboard.py
neural/shape_propagation/shape_propagator.py
neural/training/__init__.py
neural/training/device.py
neural/training/training.py
neural_dsl-0.2.4.dist-info/LICENSE.md
neural_dsl-0.2.4.dist-info/METADATA
neural_dsl-0.2.4.dist-info/WHEEL
neural_dsl-0.2.4.dist-info/entry_points.txt
neural_dsl-0.2.4.dist-info/top_level.txt
neural_dsl-0.2.4.dist-info/RECORD
