Metadata-Version: 2.1
Name: neural-dsl
Version: 0.2.4
Summary: A domain-specific language and debugger for neural networks
Home-page: https://github.com/Lemniscate-SHA-256/Neural
Author: Lemniscate-SHA-256/SENOUVO Jacques-Charles Gad
Author-email: Lemniscate_zero@proton.me
Classifier: Programming Language :: Python :: 3
Classifier: License :: OSI Approved :: MIT License
Classifier: Operating System :: OS Independent
Requires-Python: >=3.8
License-File: LICENSE.md
Requires-Dist: click
Requires-Dist: dash
Requires-Dist: dash-bootstrap-components
Requires-Dist: flask
Requires-Dist: flask-socketio
Requires-Dist: graphviz
Requires-Dist: lark
Requires-Dist: matplotlib
Requires-Dist: networkx
Requires-Dist: numpy
Requires-Dist: plotly
Requires-Dist: psutil
Requires-Dist: pytest
Requires-Dist: torch
Requires-Dist: pygithub
Requires-Dist: pyyaml
Requires-Dist: selenium
Requires-Dist: optuna
Requires-Dist: fastapi
Requires-Dist: python-dotenv
Requires-Dist: webdriver-manager
Requires-Dist: tensorflow
Requires-Dist: huggingface_hub
Requires-Dist: transformers
Requires-Dist: torchvision
Requires-Dist: multiprocess
Requires-Dist: pysnooper
Requires-Dist: onnx
Requires-Dist: flask-cors
Requires-Dist: flask-httpauth
